{
  "name": "Nguyễn Thị Ngọc Huệ",
  "tagline": "Digital Marketing Student",
  "profile_picture_url": "images/avatar/avatar.png",
  "bio_short": "Sinh viên ngành Tiếp thị Kỹ thuật số | Người đam mê Truyền thông Xã hội & Thương hiệu",
  "bio_long": "Tôi là sinh viên ngành Digital Marketing tại Đại học Văn Lang, yêu thích làm việc trong môi trường năng động và sáng tạo, nơi tôi có thể áp dụng kiến thức và trau dồi kinh nghiệm thực tế. | Tôi có niềm đam mê đặc biệt với truyền thông mạng xã hội, sáng tạo nội dung và tối ưu hóa chiến dịch marketing. | Với tinh thần ham học hỏi, tôi luôn cố gắng hoàn thiện kỹ năng để trở thành một marketer chuyên nghiệp và sáng tạo, mang đến những góc nhìn mới mẻ cho mọi dự án.",
  "contact_email": "nguyenngochue052@gmail.com",
  "phone_number": "0344794500",
  "social_links": [
    {
      "platform": "Behance",
      "url": "https://www.behance.net/hunguynngc4",
      "icon_class": "./images/Icon_socical/behance.png"
    },
    {
      "platform": "Facebook",
      "url": "https://www.facebook.com/mooncungne",
      "icon_class": "./images/Icon_socical/facebook.png"
    },
    {
      "platform": "Zalo 123",
      "url": "https://zalo.me/0344794500",
      "icon_class": "./images/Icon_socical/zalo.png"
    },
    {
      "platform": "Gmail",
      "url": "https://mail.google.com/mail/u/0/?fs=1&to=nguyenngochue052@gmail.com&tf=cm",
      "icon_class": "./images/Icon_socical/icon_gmail.png"
    }
  ],
"skills_technical": [
 "Microsoft Office",
    "Critical Thinking",
    "Digital Marketing",
    "Marketing",
    "Teamwork",
    "Content Marketing",
    "Team Leadership",
    "Market Research",
    "Communication",
    "Customer Service",
    "Online Sales",
    "Sale Conslting",
    "Amos/ SPSS (basic)"
  ],
  "skills_software": [
    "Adobe Photoshop",
    "Adobe Illustrator",
    "Adobe Premiere",
    "Microsoft Office",
    "Capcut",
    "Canva",
    "Google Space",
    "SPSS",
    "AMOS"
],
 "work_experience": [
  {
    "job_title": "Cộng tác viên Content & Tư vấn khách hàng",
    "company_name": "Hanh Phuc Wedding Decor - Ho Chi Minh",
    "company_logo_url": "images/icon_experience/icon_cay_co.png",
    "duration": "07/2021 - Nay",
    "responsibilities": [
      "Viết nội dung và đăng bài trên Fanpage Facebook (giới thiệu concept, feedback khách hàng, mini game...).",
      "Tư vấn gói dịch vụ, báo giá và chăm sóc khách hàng qua tin nhắn, điện thoại.",
      "Phối hợp chụp hình, chỉnh sửa và sản xuất nội dung truyền thông cho các sự kiện.",
      "Góp phần tăng tương tác Fanpage và thu hút khách hàng mới hàng tháng."
    ]
  },
  {
    "job_title": "Nhân viên bán hàng mỹ phẩm",
    "company_name": "The Beauty Kiwi – TP. Hồ Chí Minh",
    "company_logo_url": "images/icon_experience/icon_cay_co.png",
    "duration": "",
    "responsibilities": [
      "Tư vấn sản phẩm phù hợp với từng loại da và nhu cầu của khách hàng.",
      "Chốt đơn online và tại cửa hàng, trung bình 50–100 đơn/tháng.",
      "Học cách xử lý phản hồi và chăm sóc khách hàng sau bán hàng nhằm nâng cao trải nghiệm mua sắm."
   ]
  }
]
}

